soda/__init__.py
soda/soda.py
soda/ucsc_pdf_bbox_parser.py
soda/Gallery/LICENSE.txt
soda/Gallery/README.md
soda/Gallery/index.html
soda/Gallery/package.json
soda/Gallery/css/blueimp-gallery-indicator.css
soda/Gallery/css/blueimp-gallery-video.css
soda/Gallery/css/blueimp-gallery.css
soda/Gallery/css/blueimp-gallery.less
soda/Gallery/css/blueimp-gallery.min.css
soda/Gallery/css/blueimp-gallery.min.css.map
soda/Gallery/css/demo.css
soda/Gallery/img/error.png
soda/Gallery/img/error.svg
soda/Gallery/img/loading.gif
soda/Gallery/img/play-pause.png
soda/Gallery/img/play-pause.svg
soda/Gallery/img/video-play.png
soda/Gallery/img/video-play.svg
soda/Gallery/js/blueimp-gallery-fullscreen.js
soda/Gallery/js/blueimp-gallery-indicator.js
soda/Gallery/js/blueimp-gallery-video.js
soda/Gallery/js/blueimp-gallery-vimeo.js
soda/Gallery/js/blueimp-gallery-youtube.js
soda/Gallery/js/blueimp-gallery.js
soda/Gallery/js/blueimp-gallery.min.js
soda/Gallery/js/blueimp-gallery.min.js.map
soda/Gallery/js/blueimp-helper.js
soda/Gallery/js/demo.js
soda/Gallery/js/jquery.blueimp-gallery.js
soda/Gallery/js/jquery.blueimp-gallery.min.js
soda/Gallery/js/jquery.blueimp-gallery.min.js.map
soda/Gallery/js/vendor/jquery.js
soda/Gallery-templates/index.html
soda/octicons/.gitignore
soda/octicons/.npmignore
soda/octicons/.travis.yml
soda/octicons/CHANGELOG.md
soda/octicons/Gruntfile.js
soda/octicons/LICENSE
soda/octicons/README.md
soda/octicons/index.js
soda/octicons/index.scss
soda/octicons/package.json
soda/octicons/.github/CONTRIBUTING.md
soda/octicons/build/octicons.css
soda/octicons/build/octicons.min.css
soda/octicons/build/sprite.octicons.svg
soda/octicons/build/font/_octicons.scss
soda/octicons/build/font/octicons.css
soda/octicons/build/font/octicons.eot
soda/octicons/build/font/octicons.min.css
soda/octicons/build/font/octicons.svg
soda/octicons/build/font/octicons.ttf
soda/octicons/build/font/octicons.woff
soda/octicons/build/font/octicons.woff2
soda/octicons/build/svg/alert.svg
soda_gallery-1.0.1.dist-info/LICENSE
soda_gallery-1.0.1.dist-info/METADATA
soda_gallery-1.0.1.dist-info/WHEEL
soda_gallery-1.0.1.dist-info/entry_points.txt
soda_gallery-1.0.1.dist-info/top_level.txt
soda_gallery-1.0.1.dist-info/RECORD
