Metadata-Version: 2.1
Name: soda-gallery
Version: 1.0.1
Summary: Python-based UCSC genome browser gallery generator
Home-page: https://github.com/alexpreynolds/soda
Author: Alex Reynolds
Author-email: alexpreynolds@gmail.com
License: UNKNOWN
Platform: UNKNOWN
Classifier: Programming Language :: Python :: 3
Classifier: License :: OSI Approved :: MIT License
Classifier: Operating System :: OS Independent
Classifier: Topic :: Scientific/Engineering :: Bio-Informatics
License-File: LICENSE
Requires-Dist: requests (>=2.25.1)
Requires-Dist: certifi (>=2021.5.30)
Requires-Dist: beautifulsoup4 (>=4.9.3)
Requires-Dist: Jinja2 (>=3.0.1)
Requires-Dist: pdfminer (>=20191125)
Requires-Dist: pdfrw (>=0.4)
Requires-Dist: requests-kerberos (>=0.12.0)
